Metadata-Version: 1.0
Name: jellybean
Version: 0.0
Summary: First package attempt
Home-page: UNKNOWN
Author: UNKNOWN
Author-email: maxfairbairn1@gmail.com
License: UNKNOWN
Platform: UNKNOWN
